odoo/addons/account_invoice_supplier_ref_reuse/README.rst
odoo/addons/account_invoice_supplier_ref_reuse/__init__.py
odoo/addons/account_invoice_supplier_ref_reuse/__manifest__.py
odoo/addons/account_invoice_supplier_ref_reuse/i18n/account_invoice_supplier_ref_reuse.pot
odoo/addons/account_invoice_supplier_ref_reuse/i18n/ar.po
odoo/addons/account_invoice_supplier_ref_reuse/i18n/bg.po
odoo/addons/account_invoice_supplier_ref_reuse/i18n/bs.po
odoo/addons/account_invoice_supplier_ref_reuse/i18n/ca.po
odoo/addons/account_invoice_supplier_ref_reuse/i18n/cs.po
odoo/addons/account_invoice_supplier_ref_reuse/i18n/de.po
odoo/addons/account_invoice_supplier_ref_reuse/i18n/el_GR.po
odoo/addons/account_invoice_supplier_ref_reuse/i18n/en_GB.po
odoo/addons/account_invoice_supplier_ref_reuse/i18n/es.po
odoo/addons/account_invoice_supplier_ref_reuse/i18n/es_CR.po
odoo/addons/account_invoice_supplier_ref_reuse/i18n/es_EC.po
odoo/addons/account_invoice_supplier_ref_reuse/i18n/es_ES.po
odoo/addons/account_invoice_supplier_ref_reuse/i18n/es_MX.po
odoo/addons/account_invoice_supplier_ref_reuse/i18n/et.po
odoo/addons/account_invoice_supplier_ref_reuse/i18n/fi.po
odoo/addons/account_invoice_supplier_ref_reuse/i18n/fr.po
odoo/addons/account_invoice_supplier_ref_reuse/i18n/fr_CA.po
odoo/addons/account_invoice_supplier_ref_reuse/i18n/fr_CH.po
odoo/addons/account_invoice_supplier_ref_reuse/i18n/gl.po
odoo/addons/account_invoice_supplier_ref_reuse/i18n/hr.po
odoo/addons/account_invoice_supplier_ref_reuse/i18n/hr_HR.po
odoo/addons/account_invoice_supplier_ref_reuse/i18n/hu.po
odoo/addons/account_invoice_supplier_ref_reuse/i18n/id.po
odoo/addons/account_invoice_supplier_ref_reuse/i18n/it.po
odoo/addons/account_invoice_supplier_ref_reuse/i18n/ja.po
odoo/addons/account_invoice_supplier_ref_reuse/i18n/lt.po
odoo/addons/account_invoice_supplier_ref_reuse/i18n/mk.po
odoo/addons/account_invoice_supplier_ref_reuse/i18n/mn.po
odoo12_addon_account_invoice_supplier_ref_reuse-12.0.1.0.0.99.dev2.dist-info/METADATA
odoo12_addon_account_invoice_supplier_ref_reuse-12.0.1.0.0.99.dev2.dist-info/RECORD
odoo12_addon_account_invoice_supplier_ref_reuse-12.0.1.0.0.99.dev2.dist-info/WHEEL
odoo12_addon_account_invoice_supplier_ref_reuse-12.0.1.0.0.99.dev2.dist-info/top_level.txt
